{
    "tool_id": "simple_clicker_1763910319327",
    "version": "1.0",
    "last_used": 1763910336.1311302,
    "tool_type": "simple_clicker",
    "tool_configuration": {
        "base_priority": 5,
        "detection_branches": {
            "scenarios": [
                {
                    "id": "planting",
                    "condition": "all([k in detected_objects['default'] for k in ['base_template.png', 'hole.png']])",
                    "actions": [
                        {
                            "type": "click",
                            "templates": [
                                "hole.png"
                            ],
                            "max_items": 10,
                            "click_count": 1
                        }
                    ]
                },
                {
                    "id": "havert_crops",
                    "condition": "('base_template.png' in detected_objects['default']) and any([k in detected_objects['default'] for k in ['sunflower_crop_v2.png', 'rhubard_crop.png']])",
                    "actions": [
                        {
                            "type": "click",
                            "templates": [
                                "sunflower_crop_v2.png",
                                "rhubard_crop.png"
                            ],
                            "max_items": 10,
                            "click_count": 1
                        }
                    ]
                },
                {
                    "id": "close_basket_tool",
                    "condition": "all([k in detected_objects['default'] for k in ['basket_window.png', 'close_button.png']])",
                    "actions": [
                        {
                            "type": "click",
                            "templates": [
                                "close_button.png"
                            ],
                            "max_items": 1
                        }
                    ]
                },
                {
                    "id": "select_seed_in_basket_tool",
                    "condition": "all([k in detected_objects['default'] for k in ['basket_window.png', 'rhubard_seed.png']])",
                    "actions": [
                        {
                            "type": "click",
                            "templates": [
                                "rhubard_seed.png"
                            ],
                            "max_items": 2
                        }
                    ],
                    "childrens": [
                        "close_basket_tool"
                    ]
                },
                {
                    "id": "detect_seed_tool_not_suitable",
                    "condition": "all([k in detected_objects['default'] for k in ['base_template.png', 'basket_v2.png']]) and not ('rhubard_seed_tool.png' in detected_objects['default'])",
                    "actions": [
                        {
                            "type": "click",
                            "templates": [
                                "basket_v2.png"
                            ],
                            "max_items": 1
                        }
                    ],
                    "childrens": [
                        "select_seed_in_basket_tool"
                    ]
                },
                {
                    "id": "close_captcha",
                    "condition": "'close_text.png' in detected_objects['default']",
                    "actions": [
                        {
                            "type": "click",
                            "templates": [
                                "close_text.png"
                            ],
                            "max_items": 1
                        }
                    ]
                },
                {
                    "id": "handle_captcha",
                    "condition": "any([(k in detected_objects['captcha_passer']) for k in ['goblin', 'chest', 'skeleton']])",
                    "mode": "captcha_passer",
                    "actions": [
                        {
                            "type": "click",
                            "templates": [
                                "goblin",
                                "chest",
                                "skeleton"
                            ],
                            "max_items": 3
                        },
                        {
                            "type": "change_mode",
                            "mode": "main"
                        }
                    ],
                    "childrens": [
                        "close_captcha"
                    ]
                },
                {
                    "id": "detect_captcha",
                    "condition": "any([(k in detected_objects['default']) for k in ['attempt_left_blue.png', 'tap_chest.png', 'attempt_left_red.png']])",
                    "actions": [
                        {
                            "type": "change_mode",
                            "mode": "captcha_passer"
                        }
                    ],
                    "childrens": [
                        "handle_captcha"
                    ]
                }
            ]
        },
        "available_templates": [
            {
                "class_name": "attempt_left_blue.png",
                "path": "d:\\Sunflowerland-automation\\tools\\simple_clicker_templates\\attempt_left_blue.png"
            },
            {
                "class_name": "attempt_left_red.png",
                "path": "d:\\Sunflowerland-automation\\tools\\simple_clicker_templates\\attempt_left_red.png"
            },
            {
                "class_name": "base_template.png",
                "path": "d:\\Sunflowerland-automation\\tools\\simple_clicker_templates\\base_template.png"
            },
            {
                "class_name": "basket.png",
                "path": "d:\\Sunflowerland-automation\\tools\\simple_clicker_templates\\basket.png"
            },
            {
                "class_name": "basket_v2.png",
                "path": "d:\\Sunflowerland-automation\\tools\\simple_clicker_templates\\basket_v2.png"
            },
            {
                "class_name": "basket_window.png",
                "path": "d:\\Sunflowerland-automation\\tools\\simple_clicker_templates\\basket_window.png"
            },
            {
                "class_name": "cabbage_crop.png",
                "path": "d:\\Sunflowerland-automation\\tools\\simple_clicker_templates\\cabbage_crop.png"
            },
            {
                "class_name": "cabbage_seed.png",
                "path": "d:\\Sunflowerland-automation\\tools\\simple_clicker_templates\\cabbage_seed.png"
            },
            {
                "class_name": "cabbage_seed_v2.png",
                "path": "d:\\Sunflowerland-automation\\tools\\simple_clicker_templates\\cabbage_seed_v2.png"
            },
            {
                "class_name": "cabbage_tool_seed.png",
                "path": "d:\\Sunflowerland-automation\\tools\\simple_clicker_templates\\cabbage_tool_seed.png"
            },
            {
                "class_name": "cabbage_tool_selected.png",
                "path": "d:\\Sunflowerland-automation\\tools\\simple_clicker_templates\\cabbage_tool_selected.png"
            },
            {
                "class_name": "carrot_crop.png",
                "path": "d:\\Sunflowerland-automation\\tools\\simple_clicker_templates\\carrot_crop.png"
            },
            {
                "class_name": "cherry_tree.png",
                "path": "d:\\Sunflowerland-automation\\tools\\simple_clicker_templates\\cherry_tree.png"
            },
            {
                "class_name": "close_button.png",
                "path": "d:\\Sunflowerland-automation\\tools\\simple_clicker_templates\\close_button.png"
            },
            {
                "class_name": "close_text.png",
                "path": "d:\\Sunflowerland-automation\\tools\\simple_clicker_templates\\close_text.png"
            },
            {
                "class_name": "cook_button.png",
                "path": "d:\\Sunflowerland-automation\\tools\\simple_clicker_templates\\cook_button.png"
            },
            {
                "class_name": "exclamation.png",
                "path": "d:\\Sunflowerland-automation\\tools\\simple_clicker_templates\\exclamation.png"
            },
            {
                "class_name": "fire_pit.png",
                "path": "d:\\Sunflowerland-automation\\tools\\simple_clicker_templates\\fire_pit.png"
            },
            {
                "class_name": "fire_pit_done.png",
                "path": "d:\\Sunflowerland-automation\\tools\\simple_clicker_templates\\fire_pit_done.png"
            },
            {
                "class_name": "hole.png",
                "path": "d:\\Sunflowerland-automation\\tools\\simple_clicker_templates\\hole.png"
            },
            {
                "class_name": "planting_hole.png",
                "path": "d:\\Sunflowerland-automation\\tools\\simple_clicker_templates\\planting_hole.png"
            },
            {
                "class_name": "rhubard.png",
                "path": "d:\\Sunflowerland-automation\\tools\\simple_clicker_templates\\rhubard.png"
            },
            {
                "class_name": "rhubard_crop.png",
                "path": "d:\\Sunflowerland-automation\\tools\\simple_clicker_templates\\rhubard_crop.png"
            },
            {
                "class_name": "rhubard_seed.png",
                "path": "d:\\Sunflowerland-automation\\tools\\simple_clicker_templates\\rhubard_seed.png"
            },
            {
                "class_name": "rhubard_seed_tool.png",
                "path": "d:\\Sunflowerland-automation\\tools\\simple_clicker_templates\\rhubard_seed_tool.png"
            },
            {
                "class_name": "soybean_crop.png",
                "path": "d:\\Sunflowerland-automation\\tools\\simple_clicker_templates\\soybean_crop.png"
            },
            {
                "class_name": "sunflower_crop.png",
                "path": "d:\\Sunflowerland-automation\\tools\\simple_clicker_templates\\sunflower_crop.png"
            },
            {
                "class_name": "sunflower_crop_v2.png",
                "path": "d:\\Sunflowerland-automation\\tools\\simple_clicker_templates\\sunflower_crop_v2.png"
            },
            {
                "class_name": "sunflower_seed.png",
                "path": "d:\\Sunflowerland-automation\\tools\\simple_clicker_templates\\sunflower_seed.png"
            },
            {
                "class_name": "tap_chest.png",
                "path": "d:\\Sunflowerland-automation\\tools\\simple_clicker_templates\\tap_chest.png"
            }
        ],
        "sleep_period": 1
    }
}